flo.py
flo_chart.py-1.0.0.dist-info/LICENSE
flo_chart.py-1.0.0.dist-info/METADATA
flo_chart.py-1.0.0.dist-info/WHEEL
flo_chart.py-1.0.0.dist-info/top_level.txt
flo_chart.py-1.0.0.dist-info/RECORD
