Metadata-Version: 2.1
Name: flo-chart.py
Version: 1.0.0
Summary: Python API for downloading FLO charts
Home-page: https://github.com/gold24park/flo-chart.py
Author: Lou Park
Author-email: gold24park@gmail.com
License: MIT License
License-File: LICENSE
Requires-Dist: requests (>=2.28.2)
